{
  "folder": "v9J3JcCfGequi9aA",
  "name": "Quasar Form",
  "type": "subclass",
  "_id": "zJcjNLpJ2NnnHO5T",
  "img": "icons/magic/unholy/orb-stone-pink.webp",
  "system": {
    "description": {
      "value": "",
      "chat": ""
    },
    "source": {
      "custom": ""
    },
    "identifier": "quasar-form",
    "classIdentifier": "weapon-specialist",
    "advancement": [
      {
        "_id": "eBEUIoSfORshXzSa",
        "type": "ItemGrant",
        "configuration": {
          "items": [
            {
              "uuid": "Compendium.n5eb.t7-subclass.Item.stc36pxkupZkA32X",
              "optional": false
            },
            {
              "uuid": "Compendium.n5eb.t7-subclass.Item.MYIPrw18Im5lxfMe",
              "optional": false
            },
            {
              "uuid": "Compendium.n5eb.t7-subclass.Item.c8roERqySoelA4UV",
              "optional": false
            },
            {
              "uuid": "Compendium.n5eb.t7-subclass.Item.JDSDzW9JAEMhlEoE",
              "optional": false
            },
            {
              "uuid": "Compendium.n5eb.t7-subclass.Item.m83JXa6wu70VhBK2",
              "optional": false
            }
          ],
          "optional": false,
          "spell": null
        },
        "value": {},
        "level": 3,
        "title": "",
        "hint": ""
      },
      {
        "_id": "BlWENrDUxaaJxA67",
        "type": "ItemChoice",
        "configuration": {
          "choices": {
            "3": {
              "count": 1,
              "replacement": false
            },
            "6": {
              "count": 1,
              "replacement": false
            },
            "11": {
              "count": 1,
              "replacement": false
            },
            "16": {
              "count": 1,
              "replacement": false
            }
          },
          "allowDrops": true,
          "type": null,
          "pool": [
            {
              "uuid": "Compendium.n5eb.t7-subclass.Item.0OsirhJTX3GMmuhZ"
            },
            {
              "uuid": "Compendium.n5eb.t7-subclass.Item.hOChASYumjlNMTI9"
            },
            {
              "uuid": "Compendium.n5eb.t7-subclass.Item.I2DYFFWkE5I0Alj0"
            },
            {
              "uuid": "Compendium.n5eb.t7-subclass.Item.BsUTiajLgVht0VdA"
            },
            {
              "uuid": "Compendium.n5eb.t7-subclass.Item.EmShyR3TVV6YMaAF"
            },
            {
              "uuid": "Compendium.n5eb.t7-subclass.Item.6KvVdX9aDTK3cFQS"
            }
          ],
          "spell": null,
          "restriction": {}
        },
        "value": {
          "added": {},
          "replaced": {}
        },
        "title": "",
        "hint": ""
      },
      {
        "_id": "5cDnFc9e8Cu2GpDK",
        "type": "ItemGrant",
        "configuration": {
          "items": [
            {
              "uuid": "Compendium.n5eb.t7-subclass.Item.iOCHDqAdoDwx37Tn",
              "optional": false
            }
          ],
          "optional": false,
          "spell": null
        },
        "value": {},
        "level": 6,
        "title": "",
        "hint": ""
      },
      {
        "_id": "i4dTue4vYermc2iM",
        "type": "ItemGrant",
        "configuration": {
          "items": [
            {
              "uuid": "Compendium.n5eb.t7-subclass.Item.sNeP907VB32pcM5t",
              "optional": false
            }
          ],
          "optional": false,
          "spell": null
        },
        "value": {},
        "level": 13,
        "title": "",
        "hint": ""
      },
      {
        "_id": "vYTFq1tTZOjFwclG",
        "type": "ItemGrant",
        "configuration": {
          "items": [
            {
              "uuid": "Compendium.n5eb.t7-subclass.Item.VOiAigNiLIRoyhns",
              "optional": false
            }
          ],
          "optional": false,
          "spell": null
        },
        "value": {},
        "level": 20,
        "title": "",
        "hint": ""
      }
    ],
    "spellcasting": {
      "ninjutsu": {
        "progression": "none",
        "ability": ""
      },
      "genjutsu": {
        "progression": "none",
        "ability": ""
      },
      "taijutsu": {
        "progression": "none",
        "ability": ""
      }
    }
  },
  "effects": [],
  "sort": 0,
  "ownership": {
    "default": 0
  },
  "flags": {},
  "_stats": {
    "duplicateSource": null,
    "coreVersion": "12.331",
    "systemId": "n5eb",
    "systemVersion": "1,3,10",
    "createdTime": 1733861680748,
    "modifiedTime": 1733872403264,
    "lastModifiedBy": "n5ebbuilder00000"
  },
  "_key": "!items!zJcjNLpJ2NnnHO5T"
}
