{
  "folder": "EgaDZBBi6uN8sVgu",
  "name": "Summoner",
  "type": "subclass",
  "_id": "VGTYJ5hbD25YJrXn",
  "img": "icons/magic/symbols/triangle-glowing-green.webp",
  "system": {
    "description": {
      "value": "<p>The Ninjutsu Specialist who chose this Tradition to become a Summoner, walk the path closest to Sage hood, forming bonds with the Sage beasts across the land and in different worlds. Those who walk this path are best known for having a wide arrangement of jutsu learned from the sage creatures themselves.</p>",
      "chat": ""
    },
    "source": {
      "custom": ""
    },
    "identifier": "summoner",
    "classIdentifier": "ninjutsu-specialist",
    "advancement": [
      {
        "_id": "2vJdNjkxWy4eg6Pe",
        "type": "ItemGrant",
        "configuration": {
          "items": [
            {
              "uuid": "Compendium.n5eb.subclass.Item.t6B8MNIn54JOVGsw",
              "optional": false
            },
            {
              "uuid": "Compendium.n5eb.subclass.Item.xXoIERtvvLXAJUr8",
              "optional": false
            }
          ],
          "optional": false,
          "spell": null
        },
        "value": {},
        "level": 2,
        "title": "",
        "hint": ""
      },
      {
        "_id": "qbVJttubO2EJm5CL",
        "type": "ItemGrant",
        "configuration": {
          "items": [
            {
              "uuid": "Compendium.n5eb.subclass.Item.MlSuzoqymVCEePFQ",
              "optional": false
            },
            {
              "uuid": "Compendium.n5eb.subclass.Item.MuR98WjSrOwyAcHb",
              "optional": false
            }
          ],
          "optional": false,
          "spell": null
        },
        "value": {},
        "level": 6,
        "title": "",
        "hint": ""
      },
      {
        "_id": "viUdCB9RHZaDW8ym",
        "type": "ItemGrant",
        "configuration": {
          "items": [
            {
              "uuid": "Compendium.n5eb.subclass.Item.7NjBk2HAHtYFsFC0",
              "optional": false
            }
          ],
          "optional": false,
          "spell": null
        },
        "value": {},
        "level": 10,
        "title": "",
        "hint": ""
      },
      {
        "_id": "Gy4K4k3KRbhAodX7",
        "type": "ItemGrant",
        "configuration": {
          "items": [
            {
              "uuid": "Compendium.n5eb.subclass.Item.Nwz3ERhVhfb4uuL3",
              "optional": false
            }
          ],
          "optional": false,
          "spell": null
        },
        "value": {},
        "level": 14,
        "title": "",
        "hint": ""
      },
      {
        "_id": "AaFkZ6H9nJzqNq5B",
        "type": "ItemGrant",
        "configuration": {
          "items": [
            {
              "uuid": "Compendium.n5eb.subclass.Item.H4qC14P0PcyzR4yZ",
              "optional": false
            }
          ],
          "optional": false,
          "spell": null
        },
        "value": {},
        "level": 18,
        "title": "",
        "hint": ""
      }
    ],
    "spellcasting": {
      "ninjutsu": {
        "progression": "none",
        "ability": ""
      },
      "genjutsu": {
        "progression": "none",
        "ability": ""
      },
      "taijutsu": {
        "progression": "none",
        "ability": ""
      }
    }
  },
  "effects": [],
  "sort": 100000,
  "ownership": {
    "default": 0
  },
  "flags": {},
  "_stats": {
    "duplicateSource": null,
    "coreVersion": "12.331",
    "systemId": "n5eb",
    "systemVersion": "1,2,2",
    "createdTime": 1728702041386,
    "modifiedTime": 1728844396618,
    "lastModifiedBy": "n5ebbuilder0000"
  },
  "_key": "!items!VGTYJ5hbD25YJrXn"
}
