{
  "folder": "2CjKguasE0eNIiTl",
  "name": "Calculated Strategist",
  "type": "subclass",
  "_id": "7cw7IHDh4otsiWM5",
  "img": "icons/sundries/gaming/chess-pawn-white-glass.webp",
  "system": {
    "description": {
      "value": "<p>Some Intelligence Operatives are much more calculated than others. Their Plans are made both before and during combat. But requires much more information than others to make much more fool proof plans making use of Ninja Info cards to figure out the full capabilities of an enemy before they take direct action.</p>",
      "chat": ""
    },
    "source": {
      "custom": ""
    },
    "identifier": "calculated-strategist",
    "classIdentifier": "intelligence-operative",
    "advancement": [
      {
        "_id": "I8ZXQiklSaFVJ8F3",
        "type": "ItemGrant",
        "configuration": {
          "items": [
            {
              "uuid": "Compendium.n5eb.subclass.Item.U05AH7QfOyblzbfR",
              "optional": false
            },
            {
              "uuid": "Compendium.n5eb.subclass.Item.jMokRmnMrU4vQwqP",
              "optional": false
            }
          ],
          "optional": false,
          "spell": null
        },
        "value": {},
        "level": 3,
        "title": "",
        "hint": ""
      },
      {
        "_id": "36HduSk5jK9rFNb6",
        "type": "ItemGrant",
        "configuration": {
          "items": [
            {
              "uuid": "Compendium.n5eb.subclass.Item.b5eeGKCwjzh7yOOD",
              "optional": false
            }
          ],
          "optional": false,
          "spell": null
        },
        "value": {},
        "level": 6,
        "title": "",
        "hint": ""
      },
      {
        "_id": "pJYLM1rYbA0FkXX9",
        "type": "ItemGrant",
        "configuration": {
          "items": [
            {
              "uuid": "Compendium.n5eb.subclass.Item.569qmPID10j6Rmci",
              "optional": false
            }
          ],
          "optional": false,
          "spell": null
        },
        "value": {},
        "level": 9,
        "title": "",
        "hint": ""
      },
      {
        "_id": "e0aYTVEgob2axIgi",
        "type": "ItemGrant",
        "configuration": {
          "items": [
            {
              "uuid": "Compendium.n5eb.subclass.Item.x2iVq8Sb1KVtYoMy",
              "optional": false
            }
          ],
          "optional": false,
          "spell": null
        },
        "value": {},
        "level": 13,
        "title": "",
        "hint": ""
      },
      {
        "_id": "AEQY10DjWdglshul",
        "type": "ItemGrant",
        "configuration": {
          "items": [
            {
              "uuid": "Compendium.n5eb.subclass.Item.nTet0a6zuIdCEYdV",
              "optional": false
            }
          ],
          "optional": false,
          "spell": null
        },
        "value": {},
        "level": 17,
        "title": "",
        "hint": ""
      }
    ],
    "spellcasting": {
      "ninjutsu": {
        "progression": "none",
        "ability": ""
      },
      "genjutsu": {
        "progression": "none",
        "ability": ""
      },
      "taijutsu": {
        "progression": "none",
        "ability": ""
      }
    }
  },
  "effects": [],
  "sort": 100000,
  "ownership": {
    "default": 0
  },
  "flags": {},
  "_stats": {
    "duplicateSource": null,
    "coreVersion": "12.331",
    "systemId": "n5eb",
    "systemVersion": "1,2,2",
    "createdTime": 1728702039977,
    "modifiedTime": 1728841690958,
    "lastModifiedBy": "n5ebbuilder0000"
  },
  "_key": "!items!7cw7IHDh4otsiWM5"
}
