{
  "folder": "YGo7a3zZWqmUgNu9",
  "name": "Poorly Written Map",
  "type": "loot",
  "_id": "2tKNVlG8vOhOham6",
  "img": "icons/tools/navigation/map-marked-black.webp",
  "system": {
    "description": {
      "value": "<p>A poorly written map of a faraway homeland and its relative position to the current world.</p>",
      "chat": ""
    },
    "source": {
      "custom": "N5e"
    },
    "identified": true,
    "unidentified": {
      "description": ""
    },
    "container": null,
    "quantity": 1,
    "weight": {
      "value": 0,
      "units": "bulk"
    },
    "price": {
      "value": 0,
      "denomination": "ryo"
    },
    "rarity": "",
    "properties": [],
    "type": {
      "value": "",
      "subtype": "",
      "nestedsubtype": ""
    }
  },
  "effects": [],
  "sort": 0,
  "ownership": {
    "default": 0
  },
  "flags": {},
  "_stats": {
    "duplicateSource": null,
    "coreVersion": "12.331",
    "systemId": "n5eb",
    "systemVersion": "1,2,1",
    "createdTime": 1728700375772,
    "modifiedTime": 1728700375772,
    "lastModifiedBy": "n5ebbuilder0000"
  },
  "_key": "!items!2tKNVlG8vOhOham6"
}
