{
  "folder": "g2v8MqcemeC01ZG1",
  "name": "Futton",
  "type": "race",
  "img": "systems/n5eb/assets/Icons%20%26%20Images/Clans/Futton.png",
  "system": {
    "description": {
      "value": "<h2>A Corrosive Breath</h2><p>The Futton Clan is a clan without a clear family name, but one with a deadly history and purpose. Members of this clan can be found in villages across the country, and are used to great effect in different military institutions.</p><p>The Futton Family line is one that has a clear influence in Kirigakure (The Land of Water), even having one of its descendants as the Mizukage at one point in time. This clan uses its acidic Jutsu to melt the competition.</p><hr /><h3>Futton Traits</h3><p><strong>Recommended Ability Score Increase</strong>: +2 Int or Str, +1 Con</p><p><strong>Speed</strong>: Your base walking speed is 30 feet.</p><p><strong>Skill Proficiencies</strong>: Martial Arts, and your choice between Ninshou or Athletics.</p><p><strong>Boil Release Affinity</strong>: You begin with either Water or Fire Release Affinity. (Pick one)</p>",
      "chat": ""
    },
    "source": {
      "custom": ""
    },
    "advancement": [
      {
        "type": "AbilityScoreImprovement",
        "_id": "lBQFKAkq0XnYDncB",
        "configuration": {
          "points": 2,
          "fixed": {
            "str": 0,
            "dex": 0,
            "con": 1,
            "int": 0,
            "wis": 0,
            "cha": 0
          },
          "cap": 2
        },
        "value": {
          "type": "asi"
        },
        "level": 0,
        "title": "",
        "hint": ""
      },
      {
        "type": "Size",
        "_id": "3gN3Hm22Jv8olbS6",
        "configuration": {
          "sizes": [
            "med"
          ]
        },
        "level": 0,
        "value": {}
      },
      {
        "type": "Trait",
        "configuration": {
          "grants": [
            "languages:standard:common"
          ],
          "mode": "default",
          "allowReplacements": false,
          "choices": []
        },
        "_id": "hVI51TuhOiAwJ4YT",
        "value": {
          "chosen": []
        },
        "level": 0
      },
      {
        "_id": "vGau6R7xiLlLW3ZC",
        "type": "Trait",
        "configuration": {
          "mode": "default",
          "allowReplacements": false,
          "grants": [
            "skills:mar"
          ],
          "choices": [
            {
              "count": 1,
              "pool": [
                "skills:ath",
                "skills:nsh"
              ]
            }
          ]
        },
        "value": {
          "chosen": []
        },
        "level": 0,
        "title": "",
        "hint": ""
      },
      {
        "_id": "4KctXR3zyrYlQY7J",
        "type": "ItemGrant",
        "configuration": {
          "items": [
            {
              "uuid": "Compendium.n5eb.clan.Item.kvP4d5Otfq0uMBBF",
              "optional": false
            },
            {
              "uuid": "Compendium.n5eb.clan.Item.7CGUWbZWw92RvbOH",
              "optional": false
            },
            {
              "uuid": "Compendium.n5eb.clan.Item.la2bapZRQC45b6Da",
              "optional": false
            },
            {
              "uuid": "Compendium.n5eb.clan.Item.Gbbe4xMjjamUqpPA",
              "optional": false
            }
          ],
          "optional": false,
          "spell": null
        },
        "value": {},
        "level": 1,
        "title": "",
        "hint": ""
      },
      {
        "_id": "29EXnXEGlvnbD7z6",
        "type": "ItemGrant",
        "configuration": {
          "items": [
            {
              "uuid": "Compendium.n5eb.clan.Item.4orzH2N5byuKBTEG",
              "optional": false
            },
            {
              "uuid": "Compendium.n5eb.clan.Item.59tZTecqVp4NQ1zG",
              "optional": false
            }
          ],
          "optional": false,
          "spell": null
        },
        "value": {},
        "level": 3,
        "title": "",
        "hint": ""
      },
      {
        "_id": "w37SlAdXHL2hgs7H",
        "type": "ItemGrant",
        "configuration": {
          "items": [
            {
              "uuid": "Compendium.n5eb.clan.Item.AwaypYdPnqYD3uww",
              "optional": false
            }
          ],
          "optional": false,
          "spell": null
        },
        "value": {},
        "level": 7,
        "title": "",
        "hint": ""
      },
      {
        "_id": "yWLabC3sBtxZyN2h",
        "type": "ScaleValue",
        "configuration": {
          "identifier": "",
          "type": "number",
          "distance": {
            "units": ""
          },
          "scale": {
            "1": {
              "value": 2
            },
            "11": {
              "value": 4
            },
            "18": {
              "value": 6
            }
          }
        },
        "value": {},
        "title": "Boil Over Damage",
        "hint": ""
      },
      {
        "_id": "VSoMuVHzMChE4CkQ",
        "type": "Trait",
        "configuration": {
          "mode": "default",
          "allowReplacements": false,
          "grants": [],
          "choices": [
            {
              "count": 1,
              "pool": [
                "affinity:fire",
                "affinity:water"
              ]
            }
          ]
        },
        "value": {
          "chosen": []
        },
        "level": 1,
        "title": "",
        "hint": ""
      },
      {
        "type": "Trait",
        "configuration": {
          "mode": "default",
          "allowReplacements": false,
          "grants": [],
          "choices": [
            {
              "count": 1,
              "pool": [
                "affinity:fire",
                "affinity:water"
              ]
            }
          ]
        },
        "value": {
          "chosen": []
        },
        "level": 7,
        "title": "",
        "hint": "",
        "_id": "fPaISyB5jGTlfApt"
      }
    ],
    "movement": {
      "burrow": null,
      "climb": null,
      "fly": null,
      "swim": null,
      "walk": 30,
      "units": null,
      "hover": false
    },
    "senses": {
      "darkvision": null,
      "chakrasight": null,
      "blindsight": null,
      "tremorsense": null,
      "truesight": null,
      "units": null,
      "special": ""
    },
    "type": {
      "value": "humanoid"
    },
    "identifier": ""
  },
  "effects": [],
  "ownership": {
    "default": 0
  },
  "flags": {},
  "_stats": {
    "duplicateSource": null,
    "coreVersion": "12.331",
    "systemId": "n5eb",
    "systemVersion": "1,3,0a",
    "createdTime": 1728698693727,
    "modifiedTime": 1728904938358,
    "lastModifiedBy": "n5ebbuilder00000"
  },
  "_id": "duGJoQZnACLF1Spa",
  "sort": 0,
  "_key": "!items!duGJoQZnACLF1Spa"
}
